<root>
    <users>
        <user>
            <userID>0</userID>
            <userName>default</userName>
            <password>1234</password>
            <todos>
                <todo>
                    <todoID>0</todoID>
                    <userID>0</userID>
                    <title>Abgabe Todo Application</title>
                    <category>Work</category>
                    <dueDate>2021-01-26</dueDate>
                    <completed>true</completed>
                    <important>true</important>
                </todo>
            </todos>
        </user>
    </users>
</root>
